pyquadkey2test/__init__.py
pyquadkey2test/version.py
pyquadkey2test/_version.py
pyquadkey2test/quadkey/__init__.py
pyquadkey2test/quadkey/util.py
pyquadkey2test/quadkey/tilesystem/tilesystem.cpython-312-x86_64-linux-gnu.so
pyquadkey2test-0.3.3.post3.dist-info/WHEEL
pyquadkey2test-0.3.3.post3.dist-info/METADATA
pyquadkey2test-0.3.3.post3.dist-info/RECORD
pyquadkey2test-0.3.3.post3.dist-info/licenses/LICENSE
