Metadata-Version: 2.4
Name: pyquadkey2test
Version: 0.3.3.post3
Summary: Python implementation of geographical tiling using QuadKeys as proposed by Microsoft
Project-URL: Homepage, https://github.com/muety/pyquadkey2
Project-URL: Bug Tracker, https://github.com/muety/pyquadkey2/issues
Project-URL: Source Code, https://github.com/muety/pyquadkey2
Project-URL: Documentation, https://docs.muetsch.io/pyquadkey2/
Author-email: Ferdinand Mütsch <ferdinand@muetsch.io>
Maintainer-email: Ferdinand Mütsch <ferdinand@muetsch.io>, CoreJa <i@coreja.com>
License: Apache License
License-File: LICENSE
Keywords: geohash,geospatial,quadkey,quadtile,tiling
Classifier: Development Status :: 4 - Beta
Classifier: License :: OSI Approved :: Apache Software License
Classifier: Natural Language :: English
Classifier: Operating System :: MacOS
Classifier: Operating System :: POSIX :: Linux
Classifier: Operating System :: Unix
Classifier: Programming Language :: Cython
Classifier: Programming Language :: Python :: 3
Classifier: Topic :: Scientific/Engineering :: GIS
Classifier: Typing :: Typed
Requires-Python: >=3.10
